pytest_gitignore.py
pytest_gitignore-1.3.dist-info/top_level.txt
pytest_gitignore-1.3.dist-info/METADATA
pytest_gitignore-1.3.dist-info/entry_points.txt
pytest_gitignore-1.3.dist-info/DESCRIPTION.rst
pytest_gitignore-1.3.dist-info/metadata.json
pytest_gitignore-1.3.dist-info/WHEEL
pytest_gitignore-1.3.dist-info/RECORD
