Metadata-Version: 2.0
Name: pytest-gitignore
Version: 1.3
Summary: py.test plugin to ignore the same files as git
Home-page: https://github.com/tgs/pytest-gitignore
Author: Thomas Grenfell Smith
Author-email: smithtg@ncbi.nlm.nih.gov
License: UNKNOWN
Platform: UNKNOWN
Classifier: License :: Public Domain
Classifier: Programming Language :: Python :: 2
Classifier: Programming Language :: Python :: 3
Classifier: Topic :: Software Development :: Testing
Classifier: Intended Audience :: Developers
Classifier: Development Status :: 4 - Beta
Classifier: Topic :: Software Development :: Version Control
Requires-Dist: pytest (>=2.7)
